py416/__init__.py
py416/files.py
py416/general.py
py416/json.py
py416/scripts.py
py416/sysinfo.py
py416/variables.py
py416-0.62.dist-info/LICENSE.txt
py416-0.62.dist-info/METADATA
py416-0.62.dist-info/WHEEL
py416-0.62.dist-info/entry_points.txt
py416-0.62.dist-info/top_level.txt
py416-0.62.dist-info/RECORD
