Metadata-Version: 2.1
Name: py416
Version: 0.62
Summary: don't question my methods
Author-email: Ezio416 <ezezio416@gmail.com>
Project-URL: Homepage, https://github.com/ezio416/py416
Project-URL: Bug Tracker, https://github.com/ezio416/py416/issues
Classifier: Programming Language :: Python :: 3
Classifier: License :: OSI Approved :: MIT License
Classifier: Operating System :: OS Independent
Requires-Python: >=3.8
License-File: LICENSE.txt
Requires-Dist: py7zr >=0.20.2
Requires-Dist: py-cpuinfo >=9.0.0
Requires-Dist: send2trash >=1.8.0
